{"_id":"07cfda3e-f818-4ec9-8793-8480c4365088","name":"Carlos Albizu University-San Juan","collegeOwnership":{"_id":"9d8b32ab-8558-48d7-af93-2c3adc4680dd"},"collegeSize":null,"collegeRegion":null,"majorsOffered":[],"satScorePoints":null,"actScorePoints":null,"earningsPoints":[{"yearAfterGraduation":0,"amount":30700},{"yearAfterGraduation":2,"amount":30000},{"yearAfterGraduation":6,"amount":34000},{"yearAfterGraduation":14,"amount":92102}],"slug":"carlos-albizu-university-san-juan","postalCode":{"city":{"_id":"d82de2e1-f839-45a4-966f-d41da5ff333b","name":"San Juan","state":{"_id":"e665aa1f-c1d1-44b3-ac17-1c2f8fc37911","name":"PR"}},"metroAreaSet":{"items":[]}}}
