{"_id":"0dd506e7-ccb8-4633-974f-2ea89102e4db","name":"Alma College","collegeOwnership":{"_id":"9d8b32ab-8558-48d7-af93-2c3adc4680dd"},"collegeSize":{"_id":"a5e3462e-930a-4d0e-b992-13346e87930d"},"collegeRegion":{"_id":"77d840a1-a3dc-4541-b229-95328ec12f93"},"majorsOffered":[],"satScorePoints":[{"percentile":25,"score":1028},{"percentile":50,"score":1110},{"percentile":75,"score":1320}],"actScorePoints":[{"percentile":25,"score":21},{"percentile":50,"score":24},{"percentile":75,"score":27}],"earningsPoints":[{"yearAfterGraduation":0,"amount":32743},{"yearAfterGraduation":2,"amount":34800},{"yearAfterGraduation":6,"amount":48300},{"yearAfterGraduation":14,"amount":82100}],"slug":"alma-college","postalCode":{"city":{"_id":"2160135a-530a-43ef-8454-3daba1beb3db","name":"Alma","state":{"_id":"f22a3bca-9ef3-48ca-a175-0d308cc6ef2a","name":"Michigan"}},"metroAreaSet":{"items":[]}}}
