{"_id":"e1fa4f17-021f-4c02-9df5-3328878d92f1","name":"The College of Idaho","collegeOwnership":{"_id":"9d8b32ab-8558-48d7-af93-2c3adc4680dd"},"collegeSize":{"_id":"1827c86a-828c-4026-999b-f3e5a1b51a59"},"collegeRegion":{"_id":"548dbd0d-d7e1-42c5-99f5-cf0a13765347"},"majorsOffered":[],"satScorePoints":[{"percentile":25,"score":0},{"percentile":50,"score":0},{"percentile":75,"score":0}],"actScorePoints":null,"earningsPoints":[{"yearAfterGraduation":0,"amount":28132},{"yearAfterGraduation":2,"amount":29900},{"yearAfterGraduation":6,"amount":45700},{"yearAfterGraduation":14,"amount":81600}],"slug":"the-college-of-idaho","postalCode":{"city":{"_id":"3a4988be-1fde-4d25-b1d5-de2992316383","name":"Caldwell","state":{"_id":"9e81497f-5ca2-4b9c-b29c-a2d2fa54126b","name":"Idaho"}},"metroAreaSet":{"items":[]}}}
